incuna_auth/__init__.py
incuna_auth/backends.py
incuna_auth/forms.py
incuna_auth/models.py
incuna_auth/urls.py
incuna_auth/fixtures/admin_sso.json
incuna_auth/locale/cz/LC_MESSAGES/django.mo
incuna_auth/locale/cz/LC_MESSAGES/django.po
incuna_auth/locale/de/LC_MESSAGES/django.mo
incuna_auth/locale/de/LC_MESSAGES/django.po
incuna_auth/locale/ee/LC_MESSAGES/django.mo
incuna_auth/locale/ee/LC_MESSAGES/django.po
incuna_auth/locale/en_IE/LC_MESSAGES/django.mo
incuna_auth/locale/en_IE/LC_MESSAGES/django.po
incuna_auth/locale/es/LC_MESSAGES/django.mo
incuna_auth/locale/es/LC_MESSAGES/django.po
incuna_auth/locale/fi/LC_MESSAGES/django.mo
incuna_auth/locale/fi/LC_MESSAGES/django.po
incuna_auth/locale/fr/LC_MESSAGES/django.mo
incuna_auth/locale/fr/LC_MESSAGES/django.po
incuna_auth/locale/hr/LC_MESSAGES/django.mo
incuna_auth/locale/hr/LC_MESSAGES/django.po
incuna_auth/locale/hu/LC_MESSAGES/django.mo
incuna_auth/locale/hu/LC_MESSAGES/django.po
incuna_auth/locale/it/LC_MESSAGES/django.mo
incuna_auth/locale/it/LC_MESSAGES/django.po
incuna_auth/locale/lt/LC_MESSAGES/django.mo
incuna_auth/locale/lt/LC_MESSAGES/django.po
incuna_auth/locale/lv/LC_MESSAGES/django.mo
incuna_auth/locale/lv/LC_MESSAGES/django.po
incuna_auth/locale/nl/LC_MESSAGES/django.mo
incuna_auth/locale/nl/LC_MESSAGES/django.po
incuna_auth/locale/nl_BE/LC_MESSAGES/django.mo
incuna_auth/locale/nl_BE/LC_MESSAGES/django.po
incuna_auth/locale/pl/LC_MESSAGES/django.mo
incuna_auth/locale/pl/LC_MESSAGES/django.po
incuna_auth/locale/ro/LC_MESSAGES/django.mo
incuna_auth/locale/ro/LC_MESSAGES/django.po
incuna_auth/locale/se/LC_MESSAGES/django.mo
incuna_auth/locale/se/LC_MESSAGES/django.po
incuna_auth/locale/sl/LC_MESSAGES/django.mo
incuna_auth/locale/sl/LC_MESSAGES/django.po
incuna_auth/middleware/__init__.py
incuna_auth/middleware/basic_auth.py
incuna_auth/middleware/login_required.py
incuna_auth/middleware/login_required_feincms.py
incuna_auth/middleware/permission.py
incuna_auth/middleware/permission_feincms.py
incuna_auth-10.0.0.dist-info/LICENSE
incuna_auth-10.0.0.dist-info/METADATA
incuna_auth-10.0.0.dist-info/WHEEL
incuna_auth-10.0.0.dist-info/top_level.txt
incuna_auth-10.0.0.dist-info/RECORD
