Metadata-Version: 2.1
Name: incuna-auth
Version: 10.0.0
Summary: Provides authentication parts.
Home-page: http://github.com/incuna/incuna-auth
Author: Incuna Ltd
Author-email: admin@incuna.com
License: UNKNOWN
Platform: UNKNOWN
Requires-Dist: django-admin-sso
Requires-Dist: django-crispy-forms
